pwm_generator.v
module pwm_generator(
    input clk,              // System clock input
    input reset,            // Reset signal to initialize counter
    input enable,           // Enables/disables PWM generation
    input [3:0] duty,       // 4-bit duty cycle input (0–15)
    output pwm_out          // PWM output signal
);

    // ---------------------------------------------------------
    // Internal register declaration
    // 4-bit counter used to generate PWM time base
    // ---------------------------------------------------------
    // 4-bit counter used as the PWM time base
    reg [3:0] counter;

    // ---------------------------------------------------------
    // Counter logic
    // Counter increments at every rising clock edge
    // Counter generates one complete PWM period by counting
    // from 0 to 15. After reaching 15, it wraps back to 0.
    // ---------------------------------------------------------
   always @(posedge clk or posedge reset)
    begin
        if (reset) // Reset the counter to its initial state
            counter <= 4'd0;
        else if (enable) // Counter operates only when enable is HIGH
        begin
            // Restart counting after one PWM period
            if (counter == 4'd15)
                counter <= 4'd0;
            else
                counter <= counter + 4'd1; // Increment counter on every clock cycle
        end
    end

    // ---------------------------------------------------------
    // Comparator logic
    // PWM output remains HIGH while the counter value
    // is less than the programmed duty cycle.
    // ---------------------------------------------------------
    assign pwm_out = (counter < duty); 
endmodule

tb_pwm.v
`timescale 1ns/1ps

module tb_pwm;

    // Testbench signals
    reg clk;
    reg reset;
    reg enable;
    reg [3:0] duty;
    wire pwm_out;

    // ---------------------------------------------------------
    // Instantiate the PWM Generator
    // ---------------------------------------------------------
    pwm_generator uut (
        .clk(clk),
        .reset(reset),
        .enable(enable),
        .duty(duty),
        .pwm_out(pwm_out)
    );

    // ---------------------------------------------------------
    // Clock Generation
    // Generates a clock with a period of 10 ns
    // ---------------------------------------------------------
    initial begin
        clk = 0;
        forever #5 clk = ~clk;
    end

    // ---------------------------------------------------------
    // Test Sequence
    // ---------------------------------------------------------
    initial begin

        // Generate waveform file
        $dumpfile("wave.vcd");
        $dumpvars(0, tb_pwm);

        // Initialize signals
        reset  = 1;
        enable = 0;
        duty   = 0;

        // Hold reset for 20 ns
        #20;
        reset  = 0;
        enable = 1;

        // -----------------------------
        // Test different duty cycles
        // -----------------------------

        $display("Testing Duty = 0%");
        duty = 4'd0;
        #160;

        $display("Testing Duty = 6.25%");
        duty = 4'd1;
        #160;

        $display("Testing Duty = 25%");
        duty = 4'd4;
        #160;

        $display("Testing Duty = 50%");
        duty = 4'd8;
        #160;

        $display("Testing Duty = 75%");
        duty = 4'd12;
        #160;

        $display("Testing Duty = 93.75%");
        duty = 4'd15;
        #160;

        // -----------------------------
        // Test Enable Signal
        // -----------------------------

        $display("Disabling PWM...");
        enable = 0;
        #100;

        $display("Enabling PWM...");
        enable = 1;
        #160;

        $display("Simulation Completed Successfully.");

        $finish;

    end

endmodule

waveforms/wave.vcd
$date
	Sun Jun 28 15:29:26 2026
$end
$version
	Icarus Verilog
$end
$timescale
	1ps
$end
$scope module tb_pwm $end
$var wire 1 ! pwm_out $end
$var reg 1 " clk $end
$var reg 4 # duty [3:0] $end
$var reg 1 $ enable $end
$var reg 1 % reset $end
$scope module uut $end
$var wire 1 " clk $end
$var wire 4 & duty [3:0] $end
$var wire 1 $ enable $end
$var wire 1 % reset $end
$var wire 1 ! pwm_out $end
$var reg 4 ' counter [3:0] $end
$upscope $end
$upscope $end
$enddefinitions $end
$comment Show the parameter values. $end
$dumpall
$end
#0
$dumpvars
b0 '
b0 &
1%
0$
b0 #
0"
0!
$end
#5000
1"
#10000
0"
#15000
1"
#20000
0"
1$
0%
#25000
b1 '
1"
#30000
0"
#35000
b10 '
1"
#40000
0"
#45000
b11 '
1"
#50000
0"
#55000
b100 '
1"
#60000
0"
#65000
b101 '
1"
#70000
0"
#75000
b110 '
1"
#80000
0"
#85000
b111 '
1"
#90000
0"
#95000
b1000 '
1"
#100000
0"
#105000
b1001 '
1"
#110000
0"
#115000
b1010 '
1"
#120000
0"
#125000
b1011 '
1"
#130000
0"
#135000
b1100 '
1"
#140000
0"
#145000
b1101 '
1"
#150000
0"
#155000
b1110 '
1"
#160000
0"
#165000
b1111 '
1"
#170000
0"
#175000
b0 '
1"
#180000
0"
1!
b1 #
b1 &
#185000
0!
b1 '
1"
#190000
0"
#195000
b10 '
1"
#200000
0"
#205000
b11 '
1"
#210000
0"
#215000
b100 '
1"
#220000
0"
#225000
b101 '
1"
#230000
0"
#235000
b110 '
1"
#240000
0"
#245000
b111 '
1"
#250000
0"
#255000
b1000 '
1"
#260000
0"
#265000
b1001 '
1"
#270000
0"
#275000
b1010 '
1"
#280000
0"
#285000
b1011 '
1"
#290000
0"
#295000
b1100 '
1"
#300000
0"
#305000
b1101 '
1"
#310000
0"
#315000
b1110 '
1"
#320000
0"
#325000
b1111 '
1"
#330000
0"
#335000
1!
b0 '
1"
#340000
0"
b100 #
b100 &
#345000
b1 '
1"
#350000
0"
#355000
b10 '
1"
#360000
0"
#365000
b11 '
1"
#370000
0"
#375000
0!
b100 '
1"
#380000
0"
#385000
b101 '
1"
#390000
0"
#395000
b110 '
1"
#400000
0"
#405000
b111 '
1"
#410000
0"
#415000
b1000 '
1"
#420000
0"
#425000
b1001 '
1"
#430000
0"
#435000
b1010 '
1"
#440000
0"
#445000
b1011 '
1"
#450000
0"
#455000
b1100 '
1"
#460000
0"
#465000
b1101 '
1"
#470000
0"
#475000
b1110 '
1"
#480000
0"
#485000
b1111 '
1"
#490000
0"
#495000
1!
b0 '
1"
#500000
0"
b1000 #
b1000 &
#505000
b1 '
1"
#510000
0"
#515000
b10 '
1"
#520000
0"
#525000
b11 '
1"
#530000
0"
#535000
b100 '
1"
#540000
0"
#545000
b101 '
1"
#550000
0"
#555000
b110 '
1"
#560000
0"
#565000
b111 '
1"
#570000
0"
#575000
0!
b1000 '
1"
#580000
0"
#585000
b1001 '
1"
#590000
0"
#595000
b1010 '
1"
#600000
0"
#605000
b1011 '
1"
#610000
0"
#615000
b1100 '
1"
#620000
0"
#625000
b1101 '
1"
#630000
0"
#635000
b1110 '
1"
#640000
0"
#645000
b1111 '
1"
#650000
0"
#655000
1!
b0 '
1"
#660000
0"
b1100 #
b1100 &
#665000
b1 '
1"
#670000
0"
#675000
b10 '
1"
#680000
0"
#685000
b11 '
1"
#690000
0"
#695000
b100 '
1"
#700000
0"
#705000
b101 '
1"
#710000
0"
#715000
b110 '
1"
#720000
0"
#725000
b111 '
1"
#730000
0"
#735000
b1000 '
1"
#740000
0"
#745000
b1001 '
1"
#750000
0"
#755000
b1010 '
1"
#760000
0"
#765000
b1011 '
1"
#770000
0"
#775000
0!
b1100 '
1"
#780000
0"
#785000
b1101 '
1"
#790000
0"
#795000
b1110 '
1"
#800000
0"
#805000
b1111 '
1"
#810000
0"
#815000
1!
b0 '
1"
#820000
0"
b1111 #
b1111 &
#825000
b1 '
1"
#830000
0"
#835000
b10 '
1"
#840000
0"
#845000
b11 '
1"
#850000
0"
#855000
b100 '
1"
#860000
0"
#865000
b101 '
1"
#870000
0"
#875000
b110 '
1"
#880000
0"
#885000
b111 '
1"
#890000
0"
#895000
b1000 '
1"
#900000
0"
#905000
b1001 '
1"
#910000
0"
#915000
b1010 '
1"
#920000
0"
#925000
b1011 '
1"
#930000
0"
#935000
b1100 '
1"
#940000
0"
#945000
b1101 '
1"
#950000
0"
#955000
b1110 '
1"
#960000
0"
#965000
0!
b1111 '
1"
#970000
0"
#975000
1!
b0 '
1"
#980000
0"
0$
#985000
1"
#990000
0"
#995000
1"
#1000000
0"
#1005000
1"
#1010000
0"
#1015000
1"
#1020000
0"
#1025000
1"
#1030000
0"
#1035000
1"
#1040000
0"
#1045000
1"
#1050000
0"
#1055000
1"
#1060000
0"
#1065000
1"
#1070000
0"
#1075000
1"
#1080000
0"
1$
#1085000
b1 '
1"
#1090000
0"
#1095000
b10 '
1"
#1100000
0"
#1105000
b11 '
1"
#1110000
0"
#1115000
b100 '
1"
#1120000
0"
#1125000
b101 '
1"
#1130000
0"
#1135000
b110 '
1"
#1140000
0"
#1145000
b111 '
1"
#1150000
0"
#1155000
b1000 '
1"
#1160000
0"
#1165000
b1001 '
1"
#1170000
0"
#1175000
b1010 '
1"
#1180000
0"
#1185000
b1011 '
1"
#1190000
0"
#1195000
b1100 '
1"
#1200000
0"
#1205000
b1101 '
1"
#1210000
0"
#1215000
b1110 '
1"
#1220000
0"
#1225000
0!
b1111 '
1"
#1230000
0"
#1235000
1!
b0 '
1"
